favro_mcp/__init__.py
favro_mcp/__main__.py
favro_mcp/context.py
favro_mcp/server.py
favro_mcp/api/__init__.py
favro_mcp/api/client.py
favro_mcp/api/models.py
favro_mcp/resolvers/__init__.py
favro_mcp/resolvers/base.py
favro_mcp/resolvers/board.py
favro_mcp/resolvers/card.py
favro_mcp/resolvers/column.py
favro_mcp/resolvers/organization.py
favro_mcp/resolvers/tag.py
favro_mcp/resolvers/user.py
favro_mcp/tools/__init__.py
favro_mcp/tools/boards.py
favro_mcp/tools/cards.py
favro_mcp/tools/columns.py
favro_mcp/tools/organizations.py
favro_mcp-0.3.0.dist-info/METADATA
favro_mcp-0.3.0.dist-info/WHEEL
favro_mcp-0.3.0.dist-info/entry_points.txt
favro_mcp-0.3.0.dist-info/licenses/LICENSE
favro_mcp-0.3.0.dist-info/RECORD
